README.rst
setup.py
rutermextract/__init__.py
rutermextract/extractor.py
rutermextract/labeler.py
rutermextract/normalizer.py
rutermextract/parser.py
rutermextract/ranker.py
rutermextract/term_extractor.py
rutermextract/tokenizer.py
rutermextract.egg-info/PKG-INFO
rutermextract.egg-info/SOURCES.txt
rutermextract.egg-info/dependency_links.txt
rutermextract.egg-info/requires.txt
rutermextract.egg-info/top_level.txt