Metadata-Version: 1.1
Name: rutermextract
Version: 0.2
Summary: Term extraction for Russian language
Home-page: https://github.com/igor-shevchenko/rutermextract
Author: Igor Shevchenko
Author-email: mail@igorshevchenko.ru
License: MIT license
Download-URL: https://github.com/igor-shevchenko/rutermextract/tarball/0.2
Platform: UNKNOWN
Classifier: Development Status :: 4 - Beta
Classifier: Intended Audience :: Developers
Classifier: Intended Audience :: Science/Research
Classifier: License :: OSI Approved :: MIT License
Classifier: Natural Language :: Russian
Classifier: Programming Language :: Python
Classifier: Programming Language :: Python :: 2
Classifier: Programming Language :: Python :: 2.6
Classifier: Programming Language :: Python :: 2.7
Classifier: Programming Language :: Python :: 3
Classifier: Programming Language :: Python :: 3.3
Classifier: Topic :: Scientific/Engineering :: Information Analysis
Classifier: Topic :: Software Development :: Libraries :: Python Modules
Classifier: Topic :: Text Processing :: Linguistic
Requires: pymorphy2 (>=0.8)
Requires: enum34 (>=1.0)
